pymata_aio/__init__.py
pymata_aio/constants.py
pymata_aio/pin_data.py
pymata_aio/private_constants.py
pymata_aio/pymata3.py
pymata_aio/pymata_core._new.py
pymata_aio/pymata_core.py
pymata_aio/pymata_iot.py
pymata_aio/pymata_serial.py
pymata_aio/pymata_socket.py
utilities/__init__.py
utilities/list_serial_ports.py
pymata_aio-2.35.dist-info/METADATA
pymata_aio-2.35.dist-info/WHEEL
pymata_aio-2.35.dist-info/entry_points.txt
pymata_aio-2.35.dist-info/top_level.txt
pymata_aio-2.35.dist-info/RECORD
