Metadata-Version: 2.1
Name: pymata-aio
Version: 2.35
Summary: A Python Protocol Abstraction Library For Arduino Firmata using Python asyncio
Home-page: https://github.com/MrYsLab/pymata-aio/wiki
Author: Alan Yorinks
Author-email: MisterYsLab@gmail.com
License: GNU Affero General Public License v3 or later (AGPLv3+)
Download-URL: https://github.com/MrYsLab/pymata-aio
Keywords: Firmata,Arduino,Protocol
Platform: UNKNOWN
Classifier: Development Status :: 5 - Production/Stable
Classifier: Environment :: Other Environment
Classifier: Intended Audience :: Developers
Classifier: Intended Audience :: Education
Classifier: License :: OSI Approved :: GNU Affero General Public License v3 or later (AGPLv3+)
Classifier: Operating System :: OS Independent
Classifier: Programming Language :: Python :: 3.5
Classifier: Programming Language :: Python :: 3 :: Only
Classifier: Topic :: Utilities
Classifier: Topic :: Education
Classifier: Topic :: Home Automation
